odoo_tools_grap/__init__.py
odoo_tools_grap/__main__.py
odoo_tools_grap/cli/cli.py
odoo_tools_grap/cli/cli_create_branch.py
odoo_tools_grap/cli/cli_diff.py
odoo_tools_grap/cli/cli_generate.py
odoo_tools_grap/cli/cli_migrate.py
odoo_tools_grap/cli/click_options.py
odoo_tools_grap/cli/tools.py
odoo_tools_grap-1.3.6.dist-info/METADATA
odoo_tools_grap-1.3.6.dist-info/WHEEL
odoo_tools_grap-1.3.6.dist-info/entry_points.txt
odoo_tools_grap-1.3.6.dist-info/RECORD
