Metadata-Version: 2.4
Name: odoo-tools-grap
Version: 1.3.6
Summary: Small CLI tool for Odoo
License: AGPLv3+
Keywords: cli,odoo,GRAP
Author: Sylvain LE GAL
Author-email: sylvain.legal@grap.coop
Maintainer: Sylvain LE GAL
Maintainer-email: sylvain.legal@grap.coop
Requires-Python: >=3.9,<4.0
Classifier: License :: OSI Approved :: GNU Affero General Public License v3 or later (AGPLv3+)
Classifier: Intended Audience :: Developers
Classifier: Development Status :: 4 - Beta
Classifier: Operating System :: Unix
Classifier: Programming Language :: Python :: 3.9
Classifier: Programming Language :: Python :: 3.10
Classifier: Programming Language :: Python :: 3.11
Classifier: Programming Language :: Python :: 3.12
Classifier: Programming Language :: Python :: 3.13
Classifier: Programming Language :: Python :: 3.14
Classifier: Framework :: Odoo
Requires-Dist: GitPython
Requires-Dist: PyGithub
Requires-Dist: click
Requires-Dist: click-loglevel
Requires-Dist: git-aggregator
Requires-Dist: loguru
Requires-Dist: plumbum
Requires-Dist: single-source
Project-URL: Repository, https://gitlab.com/grap-rhone-alpes/odoo-tools-grap
